verlex/__init__.py
verlex/cli.py
verlex/client.py
verlex/errors.py
verlex-0.1.0.dist-info/METADATA
verlex-0.1.0.dist-info/WHEEL
verlex-0.1.0.dist-info/entry_points.txt
verlex-0.1.0.dist-info/licenses/LICENSE
verlex-0.1.0.dist-info/RECORD
