Metadata-Version: 2.4
Name: verlex
Version: 0.1.0
Summary: Run your code on the cheapest cloud provider automatically - Uber for Cloud Computing
Project-URL: Homepage, https://verlex.dev
Project-URL: Documentation, https://verlex.dev/docs
Author: Verlex Team
Maintainer: Verlex Team
License-Expression: Apache-2.0
License-File: LICENSE
Keywords: aws,azure,cloud,cloud-computing,cost-optimization,distributed-computing,gcp,gpu,machine-learning,orchestration,preemptible,price-comparison,serverless,spot-instances
Classifier: Development Status :: 4 - Beta
Classifier: Environment :: Console
Classifier: Framework :: AsyncIO
Classifier: Intended Audience :: Developers
Classifier: Intended Audience :: Science/Research
Classifier: License :: OSI Approved :: Apache Software License
Classifier: Operating System :: OS Independent
Classifier: Programming Language :: Python :: 3
Classifier: Programming Language :: Python :: 3.9
Classifier: Programming Language :: Python :: 3.10
Classifier: Programming Language :: Python :: 3.11
Classifier: Programming Language :: Python :: 3.12
Classifier: Topic :: Internet :: WWW/HTTP :: HTTP Servers
Classifier: Topic :: Scientific/Engineering :: Artificial Intelligence
Classifier: Topic :: System :: Distributed Computing
Classifier: Typing :: Typed
Requires-Python: >=3.9
Requires-Dist: cloudpickle>=3.0.0
Requires-Dist: httpx>=0.25.0
Provides-Extra: cli
Requires-Dist: rich>=13.0.0; extra == 'cli'
Provides-Extra: dev
Requires-Dist: black>=23.0.0; extra == 'dev'
Requires-Dist: mypy>=1.0.0; extra == 'dev'
Requires-Dist: pytest-asyncio>=0.21.0; extra == 'dev'
Requires-Dist: pytest-cov>=4.0.0; extra == 'dev'
Requires-Dist: pytest>=7.0.0; extra == 'dev'
Requires-Dist: ruff>=0.1.0; extra == 'dev'
